redshift_unloader/__init__.py
redshift_unloader/credential.py
redshift_unloader/logger.py
redshift_unloader/redshift.py
redshift_unloader/redshift_unloader.py
redshift_unloader/s3.py
redshift_unloader-0.1.4.dist-info/METADATA
redshift_unloader-0.1.4.dist-info/RECORD
redshift_unloader-0.1.4.dist-info/WHEEL
redshift_unloader-0.1.4.dist-info/top_level.txt
