Metadata-Version: 2.1
Name: redshift-unloader
Version: 0.1.4
Summary: Unload utility for Amazon Redshift
Home-page: https://github.com/cryeo/redshift-unloader
Author: Chaerim Yeo
Author-email: yeochaerim@gmail.com
License: MIT License
Platform: UNKNOWN
Classifier: Development Status :: 2 - Pre-Alpha
Classifier: License :: OSI Approved :: MIT License
Classifier: Programming Language :: Python
Classifier: Programming Language :: Python :: 3
Classifier: Programming Language :: Python :: 3.6
Classifier: Topic :: Software Development :: Libraries :: Python Modules
Requires-Python: >=3.6
Requires-Dist: boto3 (==1.7.84)
Requires-Dist: psycopg2 (==2.7.5)
Requires-Dist: psycopg2-binary (==2.7.5)
